ezcfg/__init__.py
ezcfg/config.py
ezcfg-0.1.3.dist-info/METADATA
ezcfg-0.1.3.dist-info/RECORD
ezcfg-0.1.3.dist-info/WHEEL
ezcfg-0.1.3.dist-info/top_level.txt
