Metadata-Version: 2.1
Name: ezcfg
Version: 0.1.3
Summary: Simple python configuration tool
Home-page: https://github.com/shalev67/EZconfig
Author: Yuval Shalev
Author-email: shalev67@gmail.com
License: MIT license
Keywords: ezcfg
Platform: UNKNOWN
Classifier: Development Status :: 1 - Planning
Classifier: Intended Audience :: Developers
Classifier: License :: OSI Approved :: MIT License
Classifier: Natural Language :: English
Classifier: Programming Language :: Python :: 3
Classifier: Programming Language :: Python :: 3.5
Classifier: Programming Language :: Python :: 3.6
Classifier: Programming Language :: Python :: 3.7
